tailwind/__init__.py
tailwind/apps.py
tailwind/npm.py
tailwind/utils.py
tailwind/validate.py
tailwind/app_template_v3/cookiecutter.json
tailwind/app_template_v3/hooks/pre_gen_project.py
tailwind/app_template_v3/{{cookiecutter.app_name}}/__init__.py
tailwind/app_template_v3/{{cookiecutter.app_name}}/apps.py
tailwind/app_template_v3/{{cookiecutter.app_name}}/static_src/.gitignore
tailwind/app_template_v3/{{cookiecutter.app_name}}/static_src/package.json
tailwind/app_template_v3/{{cookiecutter.app_name}}/static_src/postcss.config.js
tailwind/app_template_v3/{{cookiecutter.app_name}}/static_src/tailwind.config.js
tailwind/app_template_v3/{{cookiecutter.app_name}}/static_src/src/styles.css
tailwind/app_template_v3/{{cookiecutter.app_name}}/templates/base.html
tailwind/app_template_v4/cookiecutter.json
tailwind/app_template_v4/hooks/pre_gen_project.py
tailwind/app_template_v4/{{cookiecutter.app_name}}/__init__.py
tailwind/app_template_v4/{{cookiecutter.app_name}}/apps.py
tailwind/app_template_v4/{{cookiecutter.app_name}}/static_src/.gitignore
tailwind/app_template_v4/{{cookiecutter.app_name}}/static_src/package.json
tailwind/app_template_v4/{{cookiecutter.app_name}}/static_src/postcss.config.js
tailwind/app_template_v4/{{cookiecutter.app_name}}/static_src/src/styles.css
tailwind/app_template_v4/{{cookiecutter.app_name}}/templates/base.html
tailwind/app_template_v4_standalone/cookiecutter.json
tailwind/app_template_v4_standalone/hooks/pre_gen_project.py
tailwind/app_template_v4_standalone/{{cookiecutter.app_name}}/__init__.py
tailwind/app_template_v4_standalone/{{cookiecutter.app_name}}/apps.py
tailwind/app_template_v4_standalone/{{cookiecutter.app_name}}/static_src/src/styles.css
tailwind/app_template_v4_standalone/{{cookiecutter.app_name}}/templates/base.html
tailwind/management/__init__.py
tailwind/management/commands/__init__.py
tailwind/management/commands/tailwind.py
tailwind/templates/tailwind/tags/css.html
tailwind/templates/tailwind/tags/preload_css.html
django_tailwind-4.4.0.dist-info/METADATA
django_tailwind-4.4.0.dist-info/WHEEL
django_tailwind-4.4.0.dist-info/licenses/LICENSE
django_tailwind-4.4.0.dist-info/RECORD
