Metadata-Version: 2.4
Name: django-tailwind
Version: 4.4.0
Summary: Tailwind CSS Framework for Django projects
Project-URL: Homepage, https://github.com/timonweb/django-tailwind
Author-email: Tim Kamanin <tim@timonweb.com>
License-Expression: MIT
License-File: LICENSE
Keywords: css,django,tailwind
Classifier: Development Status :: 5 - Production/Stable
Classifier: Environment :: Web Environment
Classifier: Framework :: Django
Classifier: Framework :: Django :: 4.2
Classifier: Framework :: Django :: 5.0
Classifier: Framework :: Django :: 5.1
Classifier: Framework :: Django :: 5.2
Classifier: Intended Audience :: Developers
Classifier: License :: OSI Approved :: MIT License
Classifier: Operating System :: OS Independent
Classifier: Programming Language :: Python :: 3 :: Only
Classifier: Programming Language :: Python :: 3.11
Classifier: Programming Language :: Python :: 3.12
Classifier: Programming Language :: Python :: 3.13
Classifier: Programming Language :: Python :: 3.14
Classifier: Topic :: Software Development :: Libraries
Classifier: Topic :: Utilities
Requires-Python: >=3.11
Requires-Dist: django>=4.2.20
Requires-Dist: pytailwindcss>=0.3.0
Provides-Extra: cookiecutter
Requires-Dist: cookiecutter<3,>=2.6.0; extra == 'cookiecutter'
Provides-Extra: honcho
Requires-Dist: honcho<3,>=2.0.0; extra == 'honcho'
Provides-Extra: reload
Requires-Dist: django-browser-reload<2,>=1.21.0; extra == 'reload'
